AUTHORS.rst
CONTRIBUTORS.md
LICENSE
MANIFEST.in
README.md
requirements.txt
setup.py
tox.ini
climetlab_wekeo_datasets/__init__.py
climetlab_wekeo_datasets/utils.py
climetlab_wekeo_datasets/version
climetlab_wekeo_datasets.egg-info/PKG-INFO
climetlab_wekeo_datasets.egg-info/SOURCES.txt
climetlab_wekeo_datasets.egg-info/dependency_links.txt
climetlab_wekeo_datasets.egg-info/entry_points.txt
climetlab_wekeo_datasets.egg-info/requires.txt
climetlab_wekeo_datasets.egg-info/top_level.txt
climetlab_wekeo_datasets.egg-info/zip-safe
climetlab_wekeo_datasets/clms/__init__.py
climetlab_wekeo_datasets/clms/balticsea_analysisforecast_bgc.py
climetlab_wekeo_datasets/clms/balticsea_analysisforecast_phy.py
climetlab_wekeo_datasets/clms/balticsea_analysisforecast_wav.py
climetlab_wekeo_datasets/clms/balticsea_multiyear_bgc.py
climetlab_wekeo_datasets/clms/balticsea_multiyear_phy.py
climetlab_wekeo_datasets/clms/balticsea_reanalysis_wav.py
climetlab_wekeo_datasets/clms/clms_global_albh_1km_v1_10daily_netcdf.py
climetlab_wekeo_datasets/clms/clms_global_aldh_1km_v1_10daily_netcdf.py
climetlab_wekeo_datasets/clms/clms_global_dmp_1km_v2_10daily_netcdf.py
climetlab_wekeo_datasets/clms/clms_global_dmp_300m_v1_10daily_netcdf.py
climetlab_wekeo_datasets/clms/clms_global_fapar_1km_v1_10daily_netcdf.py
climetlab_wekeo_datasets/clms/clms_global_fapar_1km_v2_10daily_netcdf.py
climetlab_wekeo_datasets/clms/clms_global_fapar_300m_v1_10daily_netcdf.py
climetlab_wekeo_datasets/clms/clms_global_fcover_1km_v1_10daily_netcdf.py
climetlab_wekeo_datasets/clms/clms_global_fcover_1km_v2_10daily_netcdf.py
climetlab_wekeo_datasets/clms/clms_global_fcover_300m_v1_10daily_netcdf.py
climetlab_wekeo_datasets/clms/clms_global_gdmp_1km_v2_10daily_netcdf.py
climetlab_wekeo_datasets/clms/clms_global_gdmp_300m_v1_10daily_netcdf.py
climetlab_wekeo_datasets/clms/clms_global_gpp_300m_v1_10daily_netcdf.py
climetlab_wekeo_datasets/clms/clms_global_lai_1km_v1_10daily_netcdf.py
climetlab_wekeo_datasets/clms/clms_global_lai_1km_v2_10daily_netcdf.py
climetlab_wekeo_datasets/clms/clms_global_lai_300m_v1_10daily_netcdf.py
climetlab_wekeo_datasets/clms/clms_global_lst_5km_v1_10daily_daily_cycle_netcdf.py
climetlab_wekeo_datasets/clms/clms_global_lst_5km_v1_10daily_tci_netcdf.py
climetlab_wekeo_datasets/clms/clms_global_lst_5km_v1_hourly_netcdf.py
