Metadata-Version: 2.1
Name: climetlab-wekeo-datasets
Version: 0.3.0
Summary: A dataset plugin for climetlab for the WEkEO dataset
Home-page: http://github.com/wekeo/climetlab-wekeo-datasets
Author: Germano Guerrini
Author-email: germano.guerrini@exprivia.com
License: Apache License Version 2.0
Keywords: meteorology
Platform: UNKNOWN
Classifier: Development Status :: 3 - Alpha
Classifier: Intended Audience :: Developers
Classifier: License :: OSI Approved :: Apache Software License
Classifier: Programming Language :: Python :: 3
Classifier: Programming Language :: Python :: 3.7
Classifier: Programming Language :: Python :: 3.8
Classifier: Programming Language :: Python :: 3.9
Classifier: Programming Language :: Python :: Implementation :: CPython
Classifier: Programming Language :: Python :: Implementation :: PyPy
Classifier: Operating System :: OS Independent
